core/__init__.py
core/_registry.py
core/forms.py
core/model_registry.py
core/url_registry.py
core/views.py
migrations/0001_initial.py
migrations/0002_book_post_question_poll.py
migrations/__init__.py
octopus_dash-0.0.1.dist-info/METADATA
octopus_dash-0.0.1.dist-info/WHEEL
octopus_dash-0.0.1.dist-info/top_level.txt
octopus_dash-0.0.1.dist-info/RECORD
